LICENSE
README.md
pyproject.toml
hkopenai.hk_food_mcp_server.egg-info/PKG-INFO
hkopenai.hk_food_mcp_server.egg-info/SOURCES.txt
hkopenai.hk_food_mcp_server.egg-info/dependency_links.txt
hkopenai.hk_food_mcp_server.egg-info/entry_points.txt
hkopenai.hk_food_mcp_server.egg-info/requires.txt
hkopenai.hk_food_mcp_server.egg-info/top_level.txt
hkopenai/hk_food_mcp_server/__init__.py
hkopenai/hk_food_mcp_server/__main__.py
hkopenai/hk_food_mcp_server/app.py
hkopenai/hk_food_mcp_server/decorators.py
hkopenai/hk_food_mcp_server/tool_wholesale_prices_of_major_fresh_food.py
tests/test_tool_wholesale_prices.py
tests/test_tools.py